Workbook

Sheet Brands
A1: brand_id | B1: brand_name
A2: 1 | B2: Electra
A3: 2 | B3: Haro
A4: 3 | B4: Heller
A5: 4 | B5: Pure Cycles
A6: 5 | B6: Ritchey
A7: 6 | B7: Strider
A8: 7 | B8: Sun Bicycles
A9: 8 | B9: Surly
A10: 9 | B10: Trek

Sheet Pivot Table
A3: Row Labels | B3: Sum of Total price
A4: Children Bicycles | B4: 117065.71
A5: Comfort Bicycles | B5: 166458.42
A6: Cruisers Bicycles | B6: 366168.31
A7: Cyclocross Bicycles | B7: 246588.28
A8: Electric Bikes | B8: 323652.31
A9: Mountain Bikes | B9: 959818.72
A10: Road Bikes | B10: 600589.79
A11: Grand Total | B11: 2780341.5

Sheet Order_items
A1: Order_Id | B1: Item_Id | C1: Product_Id | D1: Quantity | E1: List_Price | F1: Discount | G1: Total Price | H1: Product_Name | I1: Category Name
A2: 1 | B2: 1 | C2: 20 | D2: 1 | E2: 599.99 | F2: 0.2 | G2: 599.79 | H2: Electra Townie Original 7D EQ - Women's - 2016 | I2: Cruisers Bicycles
A3: 1 | B3: 2 | C3: 8 | D3: 2 | E3: 1799.99 | F3: 0.1 | G3: 3599.91 | H3: Trek Remedy 29 Carbon Frameset - 2016 | I3: Cruisers Bicycles
A4: 1 | B4: 3 | C4: 10 | D4: 2 | E4: 1549 | F4: 0.1 | G4: 3097.95 | H4: Surly Straggler - 2016 | I4: Cruisers Bicycles
A5: 1 | B5: 4 | C5: 16 | D5: 2 | E5: 599.99 | F5: 0.1 | G5: 1199.93 | H5: Electra Townie Original 7D EQ - 2016 | I5: Cruisers Bicycles
A6: 1 | B6: 5 | C6: 4 | D6: 1 | E6: 2899.99 | F6: 0.2 | G6: 2899.79 | H6: Trek Fuel EX 8 29 - 2016 | I6: Cruisers Bicycles
A7: 2 | B7: 1 | C7: 20 | D7: 1 | E7: 599.99 | F7: 0.1 | G7: 599.92 | H7: Electra Townie Original 7D EQ - Women's - 2016 | I7: Cruisers Bicycles
A8: 2 | B8: 2 | C8: 16 | D8: 2 | E8: 599.99 | F8: 0.1 | G8: 1199.93 | H8: Electra Townie Original 7D EQ - 2016 | I8: Cruisers Bicycles
A9: 3 | B9: 1 | C9: 3 | D9: 1 | E9: 999.99 | F9: 0.1 | G9: 999.94 | H9: Surly Wednesday Frameset - 2016 | I9: Cruisers Bicycles
A10: 3 | B10: 2 | C10: 20 | D10: 1 | E10: 599.99 | F10: 0.1 | G10: 599.94 | H10: Electra Townie Original 7D EQ - Women's - 2016 | I10: Cruisers Bicycles
A11: 5 | B11: 1 | C11: 10 | D11: 2 | E11: 1549 | F11: 0.1 | G11: 3097.95 | H11: Surly Straggler - 2016 | I11: Children Bicycles
A12: 5 | B12: 2 | C12: 17 | D12: 1 | E12: 429 | F12: 0.1 | G12: 428.93 | H12: Pure Cycles Vine 8-Speed - 2016 | I12: Cyclocross Bicycles
A13: 5 | B13: 3 | C13: 26 | D13: 1 | E13: 599.99 | F13: 0.1 | G13: 599.92 | H13: Electra Townie Original 7D EQ - 2016 | I13: Cruisers Bicycles
... A1514: 578 | B1514: 2 | C1514: 25 | D1514: 2 | E1514: 499.99 | F1514: 0.2 | G1514: 999.78 | H1514: Electra Townie Original 7D - 2015/2016 | I1514: Electric Bikes
A1515: 578 | B1515: 3 | C1515: 18 | D1515: 2 | E1515: 449 | F1515: 0.1 | G1515: 897.95 | H1515: Pure Cycles Western 3-Speed - Women's - 2015/2016
A1516: 578 | B1516: 4 | C1516: 8 | D1516: 2 | E1516: 1799.99 | F1516: 0.2 | G1516: 3599.78 | H1516: Trek Remedy 29 Carbon Frameset - 2016
A1517: 579 | B1517: 1 | C1517: 7 | D1517: 2 | E1517: 3999.99 | F1517: 0.1 | G1517: 7999.93 | H1517: Trek Slash 8 27.5 - 2016
A1518: 579 | B1518: 2 | C1518: 6 | D1518: 1 | E1518: 469.99 | F1518: 0.2 | G1518: 469.79 | H1518: Surly Ice Cream Truck Frameset - 2016
A1519: 580 | B1519: 1 | C1519: 16 | D1519: 2 | E1519: 599.99 | F1519: 0.2 | G1519: 1199.78 | H1519: Electra Townie Original 7D EQ - 2016
A1520: 580 | B1520: 2 | C1520: 15 | D1520: 1 | E1520: 529.99 | F1520: 0.1 | G1520: 529.92 | H1520: Electra Moto 1 - 2016
A1521: 580 | B1521: 3 | C1521: 21 | D1521: 2 | E1521: 269.99 | F1521: 0.2 | G1521: 539.78 | H1521: Electra Cruiser 1 (24-Inch) - 2016
A1522: 580 | B1522: 4 | C1522: 9 | D1522: 2 | E1522: 2999.99 | F1522: 0.1 | G1522: 5999.91 | H1522: Trek Conduit+ - 2016
A1523: 580 | B1523: 5 | C1523: 19 | D1523: 1 | E1523: 449 | F1523: 0.2 | G1523: 448.8 | H1523: Pure Cycles William 3-Speed - 2016
A1524: 582 | B1524: 1 | C1524: 10 | D1524: 2 | E1524: 1549 | F1524: 0.2 | G1524: 3097.8 | H1524: Surly Straggler - 2016
A1525: 582 | B1525: 2 | C1525: 17 | D1525: 2 | E1525: 429 | F1525: 0.1 | G1525: 857.93 | H1525: Pure Cycles Vine 8-Speed - 2016
A1526: 584 | B1526: 1 | C1526: 19 | D1526: 1 | E1526: 449 | F1526: 0.1 | G1526: 448.93 | H1526: Pure Cycles William 3-Speed - 2016
... A4435: 1615 | B4435: 3 | C4435: 182 | D4435: 1 | E4435: 2499.99 | F4435: 0.2 | G4435: 2499.79 | H4435: Trek Domane SL 5 Disc - 2018
A4436: 4 | B4436: 1 | C4436: 2 | D4436: 2 | E4436: 749.99 | F4436: 0.1 | G4436: 1499.88 | H4436: Ritchey Timberwolf Frameset - 2016 | I4436: Cruisers Bicycles
A4437: 9 | B4437: 1 | C4437: 7 | D4437: 2 | E4437: 3999.99 | F4437: 0.1 | G4437: 7999.88 | H4437: Trek Slash 8 27.5 - 2016 | I4437: Cruisers Bicycles
A4438: 10 | B4438: 1 | C4438: 14 | D4438: 1 | E4438: 269.99 | F4438: 0.1 | G4438: 269.89 | H4438: Electra Girl's Hawaii 1 (16-inch) - 2015/2016 | I4438: Children Bicycles
A4439: 14 | B4439: 1 | C4439: 6 | D4439: 1 | E4439: 469.99 | F4439: 0.1 | G4439: 469.92 | H4439: Surly Ice Cream Truck Frameset - 2016 | I4439: Children Bicycles
A4440: 37 | B4440: 1 | C4440: 16 | D4440: 2 | E4440: 599.99 | F4440: 0.1 | G4440: 1199.93 | H4440: Electra Townie Original 7D EQ - 2016 | I4440: Children Bicycles
A4441: 42 | B4441: 1 | C4441: 19 | D4441: 1 | E4441: 449 | F4441: 0.1 | G4441: 448.95 | H4441: Pure Cycles William 3-Speed - 2016 | I4441: Cruisers Bicycles
A4442: 46 | B4442: 1 | C4442: 17 | D4442: 1 | E4442: 429 | F4442: 0.1 | G4442: 428.9 | H4442: Pure Cycles Vine 8-Speed - 2016 | I4442: Mountain Bikes
A4443: 49 | B4443: 1 | C4443: 13 | D4443: 2 | E4443: 269.99 | F4443: 0.1 | G4443: 539.91 | H4443: Electra Cruiser 1 (24-Inch) - 2016 | I4443: Mountain Bikes
A4444: 52 | B4444: 1 | C4444: 25 | D4444: 1 | E4444: 499.99 | F4444: 0.1 | G4444: 499.92 | H4444: Electra Townie Original 7D - 2015/2016 | I4444: Cruisers Bicycles
A4445: 56 | B4445: 1 | C4445: 20 | D4445: 2 | E4445: 599.99 | F4445: 0.1 | G4445: 1199.91 | H4445: Electra Townie Original 7D EQ - Women's - 2016 | I4445: Comfort Bicycles
A4446: 65 | B4446: 1 | C4446: 12 | D4446: 1 | E4446: 549.99 | F4446: 0.1 | G4446: 549.89 | H4446: Electra Townie Original 21D - 2016 | I4446: Mountain Bikes
A4447: 92 | B4447: 1 | C4447: 8 | D4447: 1 | E4447: 1799.99 | F4447: 0.1 | G4447: 1799.89 | H4447: Trek Remedy 29 Carbon Frameset - 2016 | I4447: Children Bicycles
... A4537: 577 | B4537: 1 | C4537: 3 | D4537: 2 | E4537: 999.99 | F4537: 0.2 | G4537: 1999.78 | H4537: Surly Wednesday Frameset - 2016 | I4537: Road Bikes
A4538: 581 | B4538: 1 | C4538: 8 | D4538: 2 | E4538: 1799.99 | F4538: 0.1 | G4538: 3599.91 | H4538: Trek Remedy 29 Carbon Frameset - 2016
A4539: 583 | B4539: 1 | C4539: 15 | D4539: 2 | E4539: 529.99 | F4539: 0.2 | G4539: 1059.78 | H4539: Electra Moto 1 - 2016
A4540: 589 | B4540: 1 | C4540: 15 | D4540: 2 | E4540: 529.99 | F4540: 0.1 | G4540: 1059.93 | H4540: Electra Moto 1 - 2016
A4541: 601 | B4541: 1 | C4541: 12 | D4541: 2 | E4541: 549.99 | F4541: 0.2 | G4541: 1099.78 | H4541: Electra Townie Original 21D - 2016
A4542: 611 | B4542: 1 | C4542: 16 | D4542: 2 | E4542: 599.99 | F4542: 0.1 | G4542: 1199.91 | H4542: Electra Townie Original 7D EQ - 2016
A4543: 619 | B4543: 1 | C4543: 25 | D4543: 1 | E4543: 499.99 | F4543: 0.1 | G4543: 499.92 | H4543: Electra Townie Original 7D - 2015/2016
A4544: 620 | B4544: 1 | C4544: 5 | D4544: 2 | E4544: 1320.99 | F4544: 0.2 | G4544: 2641.78 | H4544: Heller Shagamaw Frame - 2016
A4545: 621 | B4545: 1 | C4545: 17 | D4545: 2 | E4545: 429 | F4545: 0.1 | G4545: 857.93 | H4545: Pure Cycles Vine 8-Speed - 2016
A4546: 623 | B4546: 1 | C4546: 8 | D4546: 1 | E4546: 1799.99 | F4546: 0.1 | G4546: 1799.92 | H4546: Trek Remedy 29 Carbon Frameset - 2016
A4547: 626 | B4547: 1 | C4547: 15 | D4547: 1 | E4547: 529.99 | F4547: 0.2 | G4547: 529.79 | H4547: Electra Moto 1 - 2016
A4548: 628 | B4548: 1 | C4548: 15 | D4548: 2 | E4548: 529.99 | F4548: 0.1 | G4548: 1059.88 | H4548: Electra Moto 1 - 2016
A4549: 635 | B4549: 1 | C4549: 4 | D4549: 1 | E4549: 2899.99 | F4549: 0.1 | G4549: 2899.94 | H4549: Trek Fuel EX 8 29 - 2016
... A4723: 1608 | B4723: 1 | C4723: 231 | D4723: 2 | E4723: 529.99 | F4723: 0.1 | G4723: 1059.93 | H4723: Electra Cruiser Lux 3i Ladies' - 2018

Sheet Category_details
A1: category_id | B1: category_name
A2: 1 | B2: Children Bicycles
A3: 2 | B3: Comfort Bicycles
A4: 3 | B4: Cruisers Bicycles
A5: 4 | B5: Cyclocross Bicycles
A6: 5 | B6: Electric Bikes
A7: 6 | B7: Mountain Bikes
A8: 7 | B8: Road Bikes

Sheet Orders
A1: order_id | B1: customer_id | C1: order_status | D1: order_date | E1: required_date | F1: shipped_date | G1: store_id | H1: staff_id | I1: shipping_status
A2: 1 | B2: 259 | C2: 4 | D2: 42370 | E2: 42372 | F2: 42372 | G2: 1 | H2: 2 | I2: Delivered
A3: 2 | B3: 1212 | C3: 4 | D3: 42370 | E3: 42373 | F3: 42372 | G3: 2 | H3: 6 | I3: Delivered
A4: 3 | B4: 523 | C4: 4 | D4: 42401 | E4: 42374 | F4: 42372 | G4: 2 | H4: 7 | I4: Delivered
A5: 4 | B5: 175 | C5: 4 | D5: 42430 | E5: 42373 | F5: 42374 | G5: 1 | H5: 3 | I5: Delivered
A6: 5 | B6: 1324 | C6: 4 | D6: 42430 | E6: 42375 | F6: 42375 | G6: 2 | H6: 6 | I6: Delivered
A7: 6 | B7: 94 | C7: 4 | D7: 42461 | E7: 42376 | F7: 42374 | G7: 2 | H7: 6 | I7: Delivered
A8: 7 | B8: 324 | C8: 4 | D8: 42461 | E8: 42376 | F8: 42374 | G8: 2 | H8: 6 | I8: Delivered
A9: 8 | B9: 1204 | C9: 4 | D9: 42461 | E9: 42374 | F9: 42374 | G9: 2 | H9: 7 | I9: Delivered
A10: 9 | B10: 60 | C10: 4 | D10: 42491 | E10: 42377 | F10: 42377 | G10: 1 | H10: 2 | I10: Delivered
A11: 10 | B11: 442 | C11: 4 | D11: 42491 | E11: 42375 | F11: 42375 | G11: 2 | H11: 6 | I11: Delivered
A12: 11 | B12: 1326 | C12: 4 | D12: 42491 | E12: 42377 | F12: 42376 | G12: 2 | H12: 7 | I12: Delivered
A13: 12 | B13: 91 | C13: 4 | D13: 42522 | E13: 42377 | F13: 42378 | G13: 1 | H13: 2 | I13: Delivered
... A18: 17 | B18: 1175 | C18: 4 | D18: 42705 | E18: 42383 | F18: 42383 | G18: 1 | H18: 3 | I18: Delivered
A19: 18 | B19: 541 | C19: 4 | D19: 01-14-16 | E19: 42386 | F19: 42384 | G19: 1 | H19: 3 | I19: Delivered
A20: 19 | B20: 696 | C20: 4 | D20: 01-14-16 | E20: 42386 | F20: 42385 | G20: 1 | H20: 2 | I20: Delivered
A21: 20 | B21: 923 | C21: 4 | D21: 01-14-16 | E21: 42385 | F21: 42386 | G21: 1 | H21: 2 | I21: Delivered
A22: 21 | B22: 1250 | C22: 4 | D22: 01-15-16 | E22: 42385 | F22: 42387 | G22: 2 | H22: 6 | I22: Delivered
A23: 22 | B23: 1035 | C23: 4 | D23: 01-16-16 | E23: 42387 | F23: 42386 | G23: 1 | H23: 2 | I23: Delivered
A24: 23 | B24: 1149 | C24: 4 | D24: 01-16-16 | E24: 42388 | F24: 42388 | G24: 1 | H24: 2 | I24: Delivered
A25: 24 | B25: 636 | C25: 4 | D25: 01-18-16 | E25: 42389 | F25: 42388 | G25: 2 | H25: 7 | I25: Delivered
A26: 25 | B26: 657 | C26: 4 | D26: 01-18-16 | E26: 42390 | F26: 42390 | G26: 2 | H26: 6 | I26: Delivered
A27: 26 | B27: 1280 | C27: 4 | D27: 01-18-16 | E27: 42390 | F27: 42388 | G27: 2 | H27: 7 | I27: Delivered
A28: 27 | B28: 57 | C28: 4 | D28: 01-19-16 | E28: 42390 | F28: 42389 | G28: 2 | H28: 7 | I28: Delivered
A29: 28 | B29: 252 | C29: 4 | D29: 01-19-16 | E29: 42389 | F29: 42390 | G29: 2 | H29: 6 | I29: Delivered
A30: 29 | B30: 437 | C30: 4 | D30: 01-20-16 | E30: 42391 | F30: 42390 | G30: 2 | H30: 6 | I30: Delivered
... A51: 50 | B51: 872 | C51: 4 | D51: 01-31-16 | E51: 42403 | F51: 42402 | G51: 3 | H51: 8 | I51: Delivered
A52: 51 | B52: 1047 | C52: 4 | D52: 42371 | E52: 42402 | F52: 42403 | G52: 2 | H52: 7 | I52: Delivered
A53: 52 | B53: 767 | C53: 4 | D53: 42431 | E53: 42404 | F53: 42405 | G53: 1 | H53: 2 | I53: Delivered
A54: 53 | B54: 965 | C54: 4 | D54: 42431 | E54: 42404 | F54: 42405 | G54: 2 | H54: 6 | I54: Delivered
A55: 54 | B55: 535 | C55: 4 | D55: 42462 | E55: 42407 | F55: 42407 | G55: 2 | H55: 7 | I55: Delivered
A56: 55 | B56: 1173 | C56: 4 | D56: 42462 | E56: 42407 | F56: 42406 | G56: 2 | H56: 6 | I56: Delivered
A57: 56 | B57: 1241 | C57: 4 | D57: 42462 | E57: 42406 | F57: 42407 | G57: 2 | H57: 6 | I57: Delivered
A58: 57 | B58: 1305 | C58: 4 | D58: 42462 | E58: 42406 | F58: 42406 | G58: 2 | H58: 7 | I58: Delivered
A59: 58 | B59: 504 | C59: 4 | D59: 42492 | E59: 42407 | F59: 42407 | G59: 2 | H59: 6 | I59: Delivered
A60: 59 | B60: 563 | C60: 4 | D60: 42492 | E60: 42407 | F60: 42406 | G60: 2 | H60: 7 | I60: Delivered
A61: 60 | B61: 151 | C61: 4 | D61: 42523 | E61: 42408 | F61: 42407 | G61: 1 | H61: 3 | I61: Delivered
A62: 61 | B62: 277 | C62: 4 | D62: 42523 | E62: 42409 | F62: 42409 | G62: 2 | H62: 7 | I62: Delivered
A63: 62 | B63: 208 | C63: 4 | D63: 42553 | E63: 42410 | F63: 42410 | G63: 1 | H63: 2 | I63: Delivered
... A70: 69 | B70: 1413 | C70: 4 | D70: 42645 | E70: 42412 | F70: 42411 | G70: 2 | H70: 7 | I70: Delivered
A71: 70 | B71: 50 | C71: 3 | D71: 42676 | E71: 42411 | F71: NULL | G71: 3 | H71: 9 | I71: Shipped
A72: 71 | B72: 797 | C72: 4 | D72: 42676 | E72: 42414 | F72: 42412 | G72: 2 | H72: 7 | I72: Delivered
A73: 72 | B73: 1386 | C73: 4 | D73: 42706 | E73: 42415 | F73: 42413 | G73: 1 | H73: 2 | I73: Delivered
A74: 73 | B74: 612 | C74: 4 | D74: 42706 | E74: 42415 | F74: 42414 | G74: 2 | H74: 7 | I74: Delivered
A75: 74 | B75: 264 | C75: 4 | D75: 02-13-16 | E75: 42415 | F75: 42415 | G75: 2 | H75: 7 | I75: Delivered
A76: 75 | B76: 587 | C76: 4 | D76: 02-14-16 | E76: 42415 | F76: 42417 | G76: 2 | H76: 6 | I76: Delivered
A77: 76 | B77: 9 | C77: 3 | D77: 02-16-16 | E77: 42416 | F77: NULL | G77: 2 | H77: 6 | I77: Shipped
A78: 77 | B78: 385 | C78: 4 | D78: 02-16-16 | E78: 42419 | F78: 42419 | G78: 1 | H78: 2 | I78: Delivered
A79: 78 | B79: 1182 | C79: 4 | D79: 02-16-16 | E79: 42418 | F79: 42419 | G79: 2 | H79: 7 | I79: Delivered
A80: 79 | B80: 529 | C80: 4 | D80: 02-17-16 | E80: 42420 | F80: 42420 | G80: 1 | H80: 3 | I80: Delivered
A81: 80 | B81: 397 | C81: 4 | D81: 02-17-16 | E81: 42420 | F81: 42419 | G81: 2 | H81: 6 | I81: Delivered
A82: 81 | B82: 521 | C82: 4 | D82: 02-17-16 | E82: 42419 | F82: 42418 | G82: 2 | H82: 6 | I82: Delivered
A83: 82 | B83: 1223 | C83: 4 | D83: 02-18-16 | E83: 42421 | F83: 42420 | G83: 2 | H83: 6 | I83: Delivered
A84: 83 | B84: 393 | C84: 4 | D84: 02-19-16 | E84: 42420 | F84: 42420 | G84: 1 | H84: 3 | I84: Delivered
A85: 84 | B85: 317 | C85: 4 | D85: 02-20-16 | E85: 42422 | F85: 42421 | G85: 2 | H85: 7 | I85: Delivered
A86: 85 | B86: 1174 | C86: 4 | D86: 02-20-16 | E86: 42423 | F86: 42421 | G86: 2 | H86: 7 | I86: Delivered
A87: 86 | B87: 276 | C87: 4 | D87: 02-21-16 | E87: 42422 | F87: 42423 | G87: 2 | H87: 7 | I87: Delivered
A88: 87 | B88: 516 | C88: 4 | D88: 02-21-16 | E88: 42422 | F88: 42423 | G88: 2 | H88: 6 | I88: Delivered
A89: 88 | B89: 1069 | C89: 4 | D89: 02-21-16 | E89: 42422 | F89: 42423 | G89: 2 | H89: 6 | I89: Delivered
... A100: 99 | B100: 1165 | C100: 4 | D100: 02-29-16 | E100: 42430 | F100: 42432 | G100: 3 | H100: 9 | I100: Delivered
A101: 100 | B101: 1237 | C101: 4 | D101: 42372 | E101: 42433 | F101: 42432 | G101: 2 | H101: 7 | I101: Delivered
A102: 101 | B102: 271 | C102: 4 | D102: 42372 | E102: 42433 | F102: 42433 | G102: 3 | H102: 8 | I102: Delivered
A103: 102 | B103: 336 | C103: 4 | D103: 42403 | E103: 42434 | F103: 42432 | G103: 2 | H103: 7 | I103: Delivered
A104: 103 | B104: 991 | C104: 4 | D104: 42432 | E104: 42435 | F104: 42434 | G104: 1 | H104: 2 | I104: Delivered
A105: 104 | B105: 7 | C105: 4 | D105: 42432 | E105: 42434 | F105: 42434 | G105: 2 | H105: 7 | I105: Delivered
A106: 105 | B106: 306 | C106: 4 | D106: 42432 | E106: 42434 | F106: 42433 | G106: 2 | H106: 7 | I106: Delivered
A107: 106 | B107: 422 | C107: 4 | D107: 42463 | E107: 42434 | F107: 42434 | G107: 3 | H107: 9 | I107: Delivered
A108: 107 | B108: 633 | C108: 4 | D108: 42524 | E108: 42438 | F108: 42438 | G108: 1 | H108: 2 | I108: Delivered
A109: 108 | B109: 12 | C109: 4 | D109: 42524 | E109: 42438 | F109: 42436 | G109: 2 | H109: 6 | I109: Delivered
A110: 109 | B110: 1255 | C110: 4 | D110: 42524 | E110: 42438 | F110: 42438 | G110: 2 | H110: 6 | I110: Delivered
A111: 110 | B111: 677 | C111: 4 | D111: 42524 | E111: 42437 | F111: 42438 | G111: 3 | H111: 9 | I111: Delivered
A112: 111 | B112: 630 | C112: 4 | D112: 42554 | E112: 42439 | F112: 42439 | G112: 2 | H112: 6 | I112: Delivered
... A120: 119 | B120: 925 | C120: 4 | D120: 42707 | E120: 42443 | F120: 42443 | G120: 2 | H120: 7 | I120: Delivered
A121: 120 | B121: 327 | C121: 4 | D121: 03-14-16 | E121: 42444 | F121: 42446 | G121: 2 | H121: 7 | I121: Delivered
A122: 121 | B122: 755 | C122: 4 | D122: 03-14-16 | E122: 42444 | F122: 42445 | G122: 2 | H122: 6 | I122: Delivered
A123: 122 | B123: 786 | C123: 4 | D123: 03-14-16 | E123: 42445 | F123: 42444 | G123: 2 | H123: 6 | I123: Delivered
A124: 123 | B124: 766 | C124: 4 | D124: 03-15-16 | E124: 42447 | F124: 42446 | G124: 2 | H124: 6 | I124: Delivered
A125: 124 | B125: 403 | C125: 4 | D125: 03-16-16 | E125: 42447 | F125: 42446 | G125: 1 | H125: 3 | I125: Delivered
A126: 125 | B126: 685 | C126: 4 | D126: 03-16-16 | E126: 42448 | F126: 42446 | G126: 2 | H126: 6 | I126: Delivered
A127: 126 | B127: 1365 | C127: 4 | D127: 03-16-16 | E127: 42447 | F127: 42447 | G127: 2 | H127: 7 | I127: Delivered
A128: 127 | B128: 484 | C128: 4 | D128: 03-17-16 | E128: 42447 | F128: 42448 | G128: 3 | H128: 8 | I128: Delivered
A129: 128 | B129: 86 | C129: 4 | D129: 03-18-16 | E129: 42449 | F129: 42450 | G129: 2 | H129: 6 | I129: Delivered
A130: 129 | B130: 84 | C130: 4 | D130: 03-19-16 | E130: 42450 | F130: 42450 | G130: 2 | H130: 7 | I130: Delivered
A131: 130 | B131: 1049 | C131: 4 | D131: 03-19-16 | E131: 42451 | F131: 42449 | G131: 2 | H131: 6 | I131: Delivered
A132: 131 | B132: 316 | C132: 4 | D132: 03-19-16 | E132: 42451 | F132: 42449 | G132: 3 | H132: 8 | I132: Delivered
... A155: 154 | B155: 1286 | C155: 4 | D155: 03-31-16 | E155: 42461 | F155: 42461 | G155: 1 | H155: 2 | I155: Delivered
A156: 155 | B156: 371 | C156: 4 | D156: 42404 | E156: 42463 | F156: 42464 | G156: 2 | H156: 6 | I156: Delivered
A157: 156 | B157: 357 | C157: 4 | D157: 42433 | E157: 42466 | F157: 42465 | G157: 1 | H157: 3 | I157: Delivered
A158: 157 | B158: 43 | C158: 4 | D158: 42433 | E158: 42466 | F158: 42466 | G158: 3 | H158: 8 | I158: Delivered
A159: 158 | B159: 117 | C159: 3 | D159: 42464 | E159: 42464 | F159: NULL | G159: 3 | H159: 9 | I159: Shipped
A160: 159 | B160: 32 | C160: 4 | D160: 42464 | E160: 42466 | F160: 42466 | G160: 1 | H160: 2 | I160: Delivered
A161: 160 | B161: 205 | C161: 4 | D161: 42464 | E161: 42466 | F161: 42466 | G161: 2 | H161: 7 | I161: Delivered
A162: 161 | B162: 251 | C162: 4 | D162: 42464 | E162: 42467 | F162: 42465 | G162: 2 | H162: 7 | I162: Delivered
A163: 162 | B163: 31 | C163: 4 | D163: 42525 | E163: 42468 | F163: 42467 | G163: 1 | H163: 3 | I163: Delivered
A164: 163 | B164: 1325 | C164: 4 | D164: 42525 | E164: 42467 | F164: 42467 | G164: 2 | H164: 7 | I164: Delivered
A165: 164 | B165: 610 | C165: 4 | D165: 42555 | E165: 42468 | F165: 42469 | G165: 2 | H165: 7 | I165: Delivered
A166: 165 | B166: 574 | C166: 4 | D166: 42586 | E166: 42470 | F166: 42470 | G166: 1 | H166: 3 | I166: Delivered
A167: 166 | B167: 338 | C167: 4 | D167: 42586 | E167: 42471 | F167: 42471 | G167: 2 | H167: 6 | I167: Delivered
A168: 167 | B168: 1034 | C168: 4 | D168: 42586 | E168: 42469 | F168: 42471 | G168: 2 | H168: 7 | I168: Delivered
A169: 168 | B169: 1147 | C169: 4 | D169: 42617 | E169: 42472 | F169: 42471 | G169: 1 | H169: 3 | I169: Delivered
...

Sheet Stocks
A1: store_id | B1: product_id | C1: quantity
A2: 1 | B2: 1 | C2: 27
A3: 1 | B3: 2 | C3: 5
A4: 1 | B4: 3 | C4: 6
A5: 1 | B5: 4 | C5: 23
A6: 1 | B6: 5 | C6: 22
A7: 1 | B7: 6 | C7: 0
A8: 1 | B8: 7 | C8: 8
A9: 1 | B9: 8 | C9: 0
A10: 1 | B10: 9 | C10: 11
A11: 1 | B11: 10 | C11: 15
A12: 1 | B12: 11 | C12: 8
A13: 1 | B13: 12 | C13: 16
... A940: 3 | B940: 313 | C940: 0

Sheet Stores
A1: store_id | B1: store_name | C1: phone | D1: email | E1: street | F1: city | G1: state | H1: zip_code
A2: 1 | B2: Santa Cruz Bikes | C2: (831) 476-4321 | D2: santacruz@bikes.shop | E2: 3700 Portola Drive | F2: Santa Cruz | G2: CA | H2: 95060
A3: 2 | B3: Baldwin Bikes | C3: (516) 379-8888 | D3: baldwin@bikes.shop | E3: 4200 Chestnut Lane | F3: Baldwin | G3: NY | H3: 11432
A4: 3 | B4: Rowlett Bikes | C4: (972) 530-5555 | D4: rowlett@bikes.shop | E4: 8000 Fairway Avenue | F4: Rowlett | G4: TX | H4: 75088

Sheet Staffs
A1: staff_id | B1: first_name | C1: last_name | D1: email | E1: phone | F1: active | G1: store_id | H1: manager_id
A2: 1 | B2: Fabiola | C2: Jackson | D2: fabiola.jackson@bikes.shop | E2: (831) 555-5554 | F2: 1 | G2: 1 | H2: NULL
A3: 2 | B3: Mireya | C3: Copeland | D3: mireya.copeland@bikes.shop | E3: (831) 555-5555 | F3: 1 | G3: 1 | H3: 1
A4: 3 | B4: Genna | C4: Serrano | D4: genna.serrano@bikes.shop | E4: (831) 555-5556 | F4: 1 | G4: 1 | H4: 2
A5: 4 | B5: Virgie | C5: Wiggins | D5: virgie.wiggins@bikes.shop | E5: (831) 555-5557 | F5: 1 | G5: 1 | H5: 2
A6: 5 | B6: Jannette | C6: David | D6: jannette.david@bikes.shop | E6: (516) 379-4444 | F6: 1 | G6: 2 | H6: 1
A7: 6 | B7: Marcelene | C7: Boyer | D7: marcelene.boyer@bikes.shop | E7: (516) 379-4445 | F7: 1 | G7: 2 | H7: 5
A8: 7 | B8: Venita | C8: Daniel | D8: venita.daniel@bikes.shop | E8: (516) 379-4446 | F8: 1 | G8: 2 | H8: 5
A9: 8 | B9: Kali | C9: Vargas | D9: kali.vargas@bikes.shop | E9: (972) 530-5555 | F9: 1 | G9: 3 | H9: 1
A10: 9 | B10: Layla | C10: Terrell | D10: layla.terrell@bikes.shop | E10: (972) 530-5556 | F10: 1 | G10: 3 | H10: 7
A11: 10 | B11: Bernardine | C11: Houston | D11: bernardine.houston@bikes.shop | E11: (972) 530-5557 | F11: 1 | G11: 3 | H11: 7

Sheet SAMPLE
A3: Region | B3: Sum of Order_Id | C3: Sum of customer_id | D3: Sum of Total Price
A4: NY | B4: 864699 | C4: 751849 | D4: 1888517.5
A5: CA | B5: 297779 | C5: 208714 | D5: 592231.29
A6: TX | B6: 142442 | C6: 95924 | D6: 299592.72
A7: Total | B7: 1304920 | C7: 1056487 | D7: 2780341.5 | F7: Product with very high price | J7: Product with very Low price
F8: Row Labels | G8: Max of Total Price | J8: Row Labels | K8: Min of Total Price
F9: Trek Domane SLR 9 Disc - 2018 | G9: 23999.88 | J9: Strider Classic 12 Balance Bike - 2018 | K9: 89.79
A10: Row Labels | B10: Count of Category Name | C10: Sum of Total Price | F10: Trek Silque SLR 8 Women's - 2017 | G10: 12999.93 | J10: Sun Bicycles Lil Kitt'n - 2017 | K10: 109.79
A11: Mountain Bikes | B11: 392 | C11: 959818.72 | F11: Trek Emonda SLR 8 - 2018 | G11: 12999.91 | J11: Trek Boy's Kickster - 2015/2017 | K11: 149.79
A12: Road Bikes | B12: 126 | C12: 600589.79 | F12: Trek Silque SLR 7 Women's - 2017 | G12: 11999.93 | J12: Trek Precaliber 12 Boys - 2017 | K12: 189.79
A13: Cruisers Bicycles | B13: 466 | C13: 366168.31 | F13: Trek Domane SLR 6 Disc - 2017 | G13: 10999.93 | J13: Trek Precaliber 12 Girls - 2017 | K13: 189.79
A14: Electric Bikes | B14: 71 | C14: 323652.31 | F14: Trek Fuel EX 9.8 27.5 Plus - 2017 | G14: 10599.91 | J14: Trek Precaliber 12 Boy's - 2018 | K14: 199.94
A15: Cyclocross Bicycles | B15: 83 | C15: 246588.28 | F15: Trek Remedy 9.8 - 2017 | G15: 10599.88 | J15: Haro Shredder 20 - 2017 | K15: 209.79
A16: Comfort Bicycles | B16: 200 | C16: 166458.42 | F16: Trek Domane SL 7 Women's - 2018 | G16: 9999.93 | J16: Trek Precaliber 16 Girls - 2017 | K16: 209.79
A17: Children Bicycles | B17: 277 | C17: 117065.71 | F17: Trek Powerfly 7 FS - 2018 | G17: 9999.93 | J17: Trek Precaliber 16 Boys - 2017 | K17: 209.89
A18: Grand Total | B18: 1615 | C18: 2780341.5 | F18: Trek Powerfly 8 FS Plus - 2017 | G18: 9999.93 | J18: Trek Precaliber 16 Girl's - 2018 | K18: 209.89
F19: Trek Super Commuter+ 8S - 2018 | G19: 9999.93 | J19: Haro Shredder 20 Girls - 2017 | K19: 209.92
F20: Trek Madone 9.2 - 2017 | G20: 9999.91 | J20: Haro Shredder Pro 20 - 2017 | K20: 249.79
F21: Trek Fuel EX 9.8 29 - 2017 | G21: 9999.88 | J21: Strider Sport 16 - 2018 | K21: 249.92
F22: Trek Remedy 9.8 27.5 - 2018 | G22: 9999.78 | J22: Sun Bicycles Revolutions 24 - 2017 | K22: 250.79
F23: Trek Slash 8 27.5 - 2016 | G23: 7999.93 | J23: Sun Bicycles Revolutions 24 - Girl's - 2017 | K23: 250.79
F24: Trek Boone 7 Disc - 2018 | G24: 7999.78 | J24: Electra Cruiser 1 (24-Inch) - 2016 | K24: 269.79
F25: Trek Super Commuter+ 7 - 2018 | G25: 7199.91 | J25: Electra Girl's Hawaii 1 (16-inch) - 2015/2016 | K25: 269.79
F26: Trek Boone Race Shop Limited - 2017 | G26: 6999.93 | J26: Electra Under-The-Sea 1 16" - 2018 | K26: 279.89
F27: Trek Domane SL 6 - 2017 | G27: 6999.93 | J27: Electra Cyclosaurus 1 (16-inch) - Boy's - 2018 | K27: 279.94
F28: Trek Boone 7 - 2017 | G28: 6999.91 | J28: Electra Girl's Hawaii 1 (20-inch) - 2015/2016 | K28: 299.79
F29: Trek XM700+ - 2018 | G29: 6999.88 | J29: Electra Girl's Hawaii 1 16" - 2017 | K29: 299.79
F30: Trek XM700+ Lowstep - 2018 | G30: 6999.78 | J30: Electra Sugar Skulls 1 (20-inch) - Girl's - 2017 | K30: 299.79
... F232: Highest Price | G232: 23999.88 | J232: Lowest Price | K232: 89.79
F233: Grand Total | G233: =SUM(G9:G231) -> 611190.62 | J233: Grand Total | K233: =SUM(K9:K231) -> 422064.57

Sheet DATASHEET
A1: Order_Id | B1: customer_id | C1: first_name | D1: last_name | E1: Phone_No | F1: email | G1: street | H1: city | I1: state | J1: zip_code | K1: Item_Id | L1: Product_Id | M1: model_year | N1: store_id | O1: staff_id | P1: Quantity | Q1: List_Price | R1: Discount | S1: Total Price | T1: Product_Name | U1: Category Name | V1: o
A2: 1 | B2: 259 | C2: Johnathan | D2: Velazquez | E2: N/A | F2: johnathan.velazquez@hotmail.com | G2: 9680 E. Somerset Street | H2: Pleasanton | I2: CA | J2: 94566 | K2: 1 | L2: 20 | M2: 2016 | N2: 1 | O2: 2 | P2: 1 | Q2: 599.99 | R2: 0.2 | S2: 599.79 | T2: Electra Townie Original 7D EQ - Women's - 2016 | U2: Cruisers Bicycles
A3: 2 | B3: 1212 | C3: Jaqueline | D3: Cummings | E3: N/A | F3: jaqueline.cummings@hotmail.com | G3: 478 Wrangler St. | H3: Huntington Station | I3: NY | J3: 11746 | K3: 1 | L3: 20 | M3: 2016 | N3: 2 | O3: 6 | P3: 1 | Q3: 599.99 | R3: 0.07 | S3: 599.92 | T3: Electra Townie Original 7D EQ - Women's - 2016 | U3: Cruisers Bicycles
A4: 3 | B4: 523 | C4: Joshua | D4: Robertson | E4: N/A | F4: joshua.robertson@gmail.com | G4: 81 Campfire Court | H4: Patchogue | I4: NY | J4: 11772 | K4: 2 | L4: 20 | M4: 2016 | N4: 2 | O4: 7 | P4: 1 | Q4: 599.99 | R4: 0.05 | S4: 599.94 | T4: Electra Townie Original 7D EQ - Women's - 2016 | U4: Cruisers Bicycles
A5: 4 | B5: 175 | C5: Nova | D5: Hess | E5: N/A | F5: nova.hess@msn.com | G5: 773 South Lafayette St. | H5: Duarte | I5: CA | J5: 91010 | K5: 1 | L5: 2 | M5: 2016 | N5: 1 | O5: 3 | P5: 2 | Q5: 749.99 | R5: 0.1 | S5: 1499.88 | T5: Ritchey Timberwolf Frameset - 2016 | U5: Mountain Bikes
A6: 5 | B6: 1324 | C6: Arla | D6: Ellis | E6: N/A | F6: arla.ellis@yahoo.com | G6: 127 Crescent Ave. | H6: Utica | I6: NY | J6: 13501 | K6: 3 | L6: 26 | M6: 2016 | N6: 2 | O6: 6 | P6: 1 | Q6: 599.99 | R6: 0.07 | S6: 599.92 | T6: Electra Townie Original 7D EQ - 2016 | U6: Comfort Bicycles
A7: 6 | B7: 94 | C7: Sharyn | D7: Hopkins | E7: N/A | F7: sharyn.hopkins@hotmail.com | G7: 4 South Temple Ave. | H7: Baldwinsville | I7: NY | J7: 13027 | K7: 3 | L7: 20 | M7: 2016 | N7: 2 | O7: 6 | P7: 1 | Q7: 599.99 | R7: 0.1 | S7: 599.89 | T7: Electra Townie Original 7D EQ - Women's - 2016 | U7: Cruisers Bicycles
A8: 7 | B8: 324 | C8: Laureen | D8: Paul | E8: N/A | F8: laureen.paul@yahoo.com | G8: 617 Squaw Creek Rd. | H8: Bellmore | I8: NY | J8: 11710 | K8: 3 | L8: 17 | M8: 2016 | N8: 2 | O8: 6 | P8: 2 | Q8: 429 | R8: 0.1 | S8: 857.9 | T8: Pure Cycles Vine 8-Speed - 2016 | U8: Cruisers Bicycles
A9: 8 | B9: 1204 | C9: Leslie | D9: Higgins | E9: N/A | F9: leslie.higgins@hotmail.com | G9: 805 Logan Ave. | H9: Saratoga Springs | I9: NY | J9: 12866 | K9: 1 | L9: 22 | M9: 2016 | N9: 2 | O9: 7 | P9: 1 | Q9: 269.99 | R9: 0.05 | S9: 269.94 | T9: Electra Girl's Hawaii 1 (16-inch) - 2015/2016 | U9: Children Bicycles
A10: 9 | B10: 60 | C10: Neil | D10: Mccall | E10: N/A | F10: neil.mccall@gmail.com | G10: 7476 Oakland Dr. | H10: San Carlos | I10: CA | J10: 94070 | K10: 1 | L10: 7 | M10: 2016 | N10: 1 | O10: 2 | P10: 2 | Q10: 3999.99 | R10: 0.1 | S10: 7999.88 | T10: Trek Slash 8 27.5 - 2016 | U10: Mountain Bikes
A11: 10 | B11: 442 | C11: Alane | D11: Munoz | E11: (914) 706-7576 | F11: alane.munoz@gmail.com | G11: 8 Strawberry Dr. | H11: Yonkers | I11: NY | J11: 10701 | K11: 1 | L11: 14 | M11: 2016 | N11: 2 | O11: 6 | P11: 1 | Q11: 269.99 | R11: 0.1 | S11: 269.89 | T11: Electra Girl's Hawaii 1 (16-inch) - 2015/2016 | U11: Cruisers Bicycles
A12: 11 | B12: 1326 | C12: Tarra | D12: Guerrero | E12: N/A | F12: tarra.guerrero@aol.com | G12: 10 Baker St. | H12: Auburn | I12: NY | J12: 13021 | K12: 2 | L12: 22 | M12: 2016 | N12: 2 | O12: 7 | P12: 2 | Q12: 269.99 | R12: 0.1 | S12: 539.88 | T12: Electra Girl's Hawaii 1 (16-inch) - 2015/2016 | U12: Children Bicycles
A13: 12 | B13: 91 | C13: Marvin | D13: Mullins | E13: (619) 635-2027 | F13: marvin.mullins@aol.com | G13: 7489 Redwood Drive | H13: San Diego | I13: CA | J13: 92111 | K13: 2 | L13: 11 | M13: 2016 | N13: 1 | O13: 2 | P13: 1 | Q13: 1680.99 | R13: 0.05 | S13: 1680.94 | T13: Surly Straggler 650b - 2016 | U13: Cyclocross Bicycles
... A1616: 1615 | B1616: 136 | C1616: Sarita | D1616: Parks | E1616: N/A | F1616: sarita.parks@msn.com | G1616: 7809 Second Lane | H1616: Forney | I1616: TX | J1616: 75126 | K1616: 1 | L1616: 197 | M1616: 2018 | N1616: 3 | O1616: 8 | P1616: 2 | Q1616: 2299.99 | R1616: 0.2 | S1616: 4599.78 | T1616: Trek Verve+ Lowstep - 2018 | U1616: Electric Bikes

Sheet Products
A1: product_id | B1: product_name | C1: brand_id | D1: category_id | E1: model_year | F1: list_price | G1: Category_name
A2: 1 | B2: Trek 820 - 2016 | C2: 9 | D2: 6 | E2: 2016 | F2: 379.99 | G2: Mountain Bikes
A3: 2 | B3: Ritchey Timberwolf Frameset - 2016 | C3: 5 | D3: 6 | E3: 2016 | F3: 749.99 | G3: Mountain Bikes
A4: 3 | B4: Surly Wednesday Frameset - 2016 | C4: 8 | D4: 6 | E4: 2016 | F4: 999.99 | G4: Mountain Bikes
A5: 4 | B5: Trek Fuel EX 8 29 - 2016 | C5: 9 | D5: 6 | E5: 2016 | F5: 2899.99 | G5: Mountain Bikes
A6: 5 | B6: Heller Shagamaw Frame - 2016 | C6: 3 | D6: 6 | E6: 2016 | F6: 1320.99 | G6: Mountain Bikes
A7: 6 | B7: Surly Ice Cream Truck Frameset - 2016 | C7: 8 | D7: 6 | E7: 2016 | F7: 469.99 | G7: Mountain Bikes
A8: 7 | B8: Trek Slash 8 27.5 - 2016 | C8: 9 | D8: 6 | E8: 2016 | F8: 3999.99 | G8: Mountain Bikes
A9: 8 | B9: Trek Remedy 29 Carbon Frameset - 2016 | C9: 9 | D9: 6 | E9: 2016 | F9: 1799.99 | G9: Mountain Bikes
A10: 9 | B10: Trek Conduit+ - 2016 | C10: 9 | D10: 5 | E10: 2016 | F10: 2999.99 | G10: Mountain Bikes
A11: 10 | B11: Surly Straggler - 2016 | C11: 8 | D11: 4 | E11: 2016 | F11: 1549 | G11: Mountain Bikes
A12: 11 | B12: Surly Straggler 650b - 2016 | C12: 8 | D12: 4 | E12: 2016 | F12: 1680.99 | G12: Mountain Bikes
A13: 12 | B13: Electra Townie Original 21D - 2016 | C13: 1 | D13: 3 | E13: 2016 | F13: 549.99 | G13: Mountain Bikes
... A322: 321 | B322: Trek Checkpoint ALR Frameset - 2019 | C322: 9 | D322: 7 | E322: 2019 | F322: 3199.99 | G322: Mountain Bikes

Sheet VLOOKUP
A1: product_id | B1: product_name | C1: Category Id
A2: 20 | B2: =VLOOKUP(A2,Products!$A$1:$F$322,2,FALSE) -> Electra Townie Original 7D EQ - Women's - 2016 | C2: =VLOOKUP(A2,Products!A2:$D$322,4,0) -> 3
A3: 8 | B3: =VLOOKUP(A3,Products!$A$1:$F$322,2,FALSE) -> Trek Remedy 29 Carbon Frameset - 2016 | C3: =VLOOKUP(A3,Products!A3:$D$322,4,0) -> 6
A4: 10 | B4: =VLOOKUP(A4,Products!$A$1:$F$322,2,FALSE) -> Surly Straggler - 2016 | C4: =VLOOKUP(A4,Products!A4:$D$322,4,0) -> 4
A5: 16 | B5: =VLOOKUP(A5,Products!$A$1:$F$322,2,FALSE) -> Electra Townie Original 7D EQ - 2016 | C5: =VLOOKUP(A5,Products!A5:$D$322,4,0) -> 3
A6: 4 | B6: =VLOOKUP(A6,Products!$A$1:$F$322,2,FALSE) -> Trek Fuel EX 8 29 - 2016 | C6: =VLOOKUP(A6,Products!A6:$D$322,4,0) -> #N/A
A7: 20 | B7: =VLOOKUP(A7,Products!$A$1:$F$322,2,FALSE) -> Electra Townie Original 7D EQ - Women's - 2016 | C7: =VLOOKUP(A7,Products!A7:$D$322,4,0) -> 3
A8: 16 | B8: =VLOOKUP(A8,Products!$A$1:$F$322,2,FALSE) -> Electra Townie Original 7D EQ - 2016 | C8: =VLOOKUP(A8,Products!A8:$D$322,4,0) -> 3
A9: 3 | B9: =VLOOKUP(A9,Products!$A$1:$F$322,2,FALSE) -> Surly Wednesday Frameset - 2016 | C9: =VLOOKUP(A9,Products!A9:$D$322,4,0) -> #N/A
A10: 20 | B10: =VLOOKUP(A10,Products!$A$1:$F$322,2,FALSE) -> Electra Townie Original 7D EQ - Women's - 2016 | C10: =VLOOKUP(A10,Products!A10:$D$322,4,FALSE) -> 3
A11: 2 | B11: =VLOOKUP(A11,Products!$A$1:$F$322,2,FALSE) -> Ritchey Timberwolf Frameset - 2016 | C11: =VLOOKUP(A11,Products!A11:$D$322,4,FALSE) -> #N/A
A12: 10 | B12: =VLOOKUP(A12,Products!$A$1:$F$322,2,FALSE) -> Surly Straggler - 2016 | C12: =VLOOKUP(A12,Products!A12:$D$322,4,FALSE) -> #N/A
A13: 17 | B13: =VLOOKUP(A13,Products!$A$1:$F$322,2,FALSE) -> Pure Cycles Vine 8-Speed - 2016 | C13: =VLOOKUP(A13,Products!A13:$D$322,4,FALSE) -> 3
A14: 26 | B14: =VLOOKUP(A14,Products!$A$1:$F$322,2,FALSE) -> Electra Townie Original 7D EQ - 2016 | C14: =VLOOKUP(A14,Products!A14:$D$322,4,FALSE) -> 2
A15: 18 | B15: =VLOOKUP(A15,Products!$A$1:$F$322,2,FALSE) -> Pure Cycles Western 3-Speed - Women's - 2015/2016 | C15: =VLOOKUP(A15,Products!A15:$D$322,4,FALSE) -> 3
A16: 12 | B16: =VLOOKUP(A16,Products!$A$1:$F$322,2,FALSE) -> Electra Townie Original 21D - 2016 | C16: =VLOOKUP(A16,Products!A16:$D$322,4,FALSE) -> #N/A
A17: 20 | B17: =VLOOKUP(A17,Products!$A$1:$F$322,2,FALSE) -> Electra Townie Original 7D EQ - Women's - 2016 | C17: =VLOOKUP(A17,Products!A17:$D$322,4,FALSE) -> 3
A18: 3 | B18: =VLOOKUP(A18,Products!$A$1:$F$322,2,FALSE) -> Surly Wednesday Frameset - 2016 | C18: =VLOOKUP(A18,Products!A18:$D$322,4,FALSE) -> #N/A
A19: 9 | B19: =VLOOKUP(A19,Products!$A$1:$F$322,2,FALSE) -> Trek Conduit+ - 2016 | C19: =VLOOKUP(A19,Products!A19:$D$322,4,FALSE) -> #N/A
A20: 15 | B20: =VLOOKUP(A20,Products!$A$1:$F$322,2,FALSE) -> Electra Moto 1 - 2016 | C20: =VLOOKUP(A20,Products!A20:$D$322,4,FALSE) -> #N/A
A21: 3 | B21: =VLOOKUP(A21,Products!$A$1:$F$322,2,FALSE) -> Surly Wednesday Frameset - 2016 | C21: =VLOOKUP(A21,Products!A21:$D$322,4,FALSE) -> #N/A
... A322: 22 | B322: =VLOOKUP(A322,Products!$A$1:$F$322,2,FALSE) -> Electra Girl's Hawaii 1 (16-inch) - 2015/2016 | C322: =VLOOKUP(A322,Products!A322:$D$322,4,FALSE) -> #N/A
A323: 6 | B323: =VLOOKUP(A323,Products!$A$1:$F$322,2,FALSE) -> Surly Ice Cream Truck Frameset - 2016 | C323: =VLOOKUP(A323,Products!A$322:$D323,4,FALSE) -> #N/A
A324: 14 | B324: =VLOOKUP(A324,Products!$A$1:$F$322,2,FALSE) -> Electra Girl's Hawaii 1 (16-inch) - 2015/2016 | C324: =VLOOKUP(A324,Products!A$322:$D324,4,FALSE) -> #N/A
A325: 14 | B325: =VLOOKUP(A325,Products!$A$1:$F$322,2,FALSE) -> Electra Girl's Hawaii 1 (16-inch) - 2015/2016 | C325: =VLOOKUP(A325,Products!A$322:$D325,4,FALSE) -> #N/A
A326: 12 | B326: =VLOOKUP(A326,Products!$A$1:$F$322,2,FALSE) -> Electra Townie Original 21D - 2016 | C326: =VLOOKUP(A326,Products!A$322:$D326,4,FALSE) -> #N/A
A327: 23 | B327: =VLOOKUP(A327,Products!$A$1:$F$322,2,FALSE) -> Electra Girl's Hawaii 1 (20-inch) - 2015/2016 | C327: =VLOOKUP(A327,Products!A$322:$D327,4,FALSE) -> #N/A
A328: 25 | B328: =VLOOKUP(A328,Products!$A$1:$F$322,2,FALSE) -> Electra Townie Original 7D - 2015/2016 | C328: =VLOOKUP(A328,Products!A$322:$D328,4,FALSE) -> #N/A
A329: 24 | B329: =VLOOKUP(A329,Products!$A$1:$F$322,2,FALSE) -> Electra Townie Original 21D - 2016 | C329: =VLOOKUP(A329,Products!A$322:$D329,4,FALSE) -> #N/A
A330: 5 | B330: =VLOOKUP(A330,Products!$A$1:$F$322,2,FALSE) -> Heller Shagamaw Frame - 2016 | C330: =VLOOKUP(A330,Products!A$322:$D330,4,FALSE) -> #N/A
A331: 12 | B331: =VLOOKUP(A331,Products!$A$1:$F$322,2,FALSE) -> Electra Townie Original 21D - 2016 | C331: =VLOOKUP(A331,Products!A$322:$D331,4,FALSE) -> #N/A
A332: 24 | B332: =VLOOKUP(A332,Products!$A$1:$F$322,2,FALSE) -> Electra Townie Original 21D - 2016 | C332: =VLOOKUP(A332,Products!A$322:$D332,4,FALSE) -> #N/A
A333: 6 | B333: =VLOOKUP(A333,Products!$A$1:$F$322,2,FALSE) -> Surly Ice Cream Truck Frameset - 2016 | C333: =VLOOKUP(A333,Products!A$322:$D333,4,FALSE) -> #N/A
A334: 23 | B334: =VLOOKUP(A334,Products!$A$1:$F$322,2,FALSE) -> Electra Girl's Hawaii 1 (20-inch) - 2015/2016 | C334: =VLOOKUP(A334,Products!A$322:$D334,4,FALSE) -> #N/A
... A4723: 182 | B4723: =VLOOKUP(A4723,Products!$A$1:$F$322,2,FALSE) -> Trek Domane SL 5 Disc - 2018 | C4723: =VLOOKUP(A4723,Products!A$322:$D4723,4,FALSE) -> #N/A
C4724: =VLOOKUP(A4724,Products!A$322:$D4724,4,FALSE) -> #N/A
C4725: =VLOOKUP(A4725,Products!A$322:$D4725,4,FALSE) -> #N/A
C4726: =VLOOKUP(A4726,Products!A$322:$D4726,4,FALSE) -> #N/A
C4727: =VLOOKUP(A4727,Products!A$322:$D4727,4,FALSE) -> #N/A
